cafelogin/__init__.py
cafelogin/__main__.py
cafelogin/actions.py
cafelogin/console.py
cafelogin/portals/__init__.py
cafelogin/portals/login.py
cafelogin/portals/portal_list.py
cafelogin/portals/portal_wi2.py
cafelogin/portals/util.py
cafelogin/print_util.py
cafelogin-0.2.5.dist-info/entry_points.txt
cafelogin-0.2.5.dist-info/LICENSE
cafelogin-0.2.5.dist-info/WHEEL
cafelogin-0.2.5.dist-info/METADATA
cafelogin-0.2.5.dist-info/RECORD
