Metadata-Version: 2.1
Name: cafelogin
Version: 0.2.5
Summary: Login to wifi portals commonly found at cafes.
Home-page: https://github.com/bennord/cafelogin
License: MIT
Author: Ben Nordstrom
Author-email: bennord@gmail.com
Requires-Python: >=3.11,<4.0
Classifier: License :: OSI Approved :: MIT License
Classifier: Programming Language :: Python :: 3
Classifier: Programming Language :: Python :: 3.11
Requires-Dist: ConfigArgParse (>=1.2.3,<2.0.0)
Requires-Dist: colorama (>=0.4.4,<0.5.0)
Requires-Dist: selenium (>=3.14.1,<4.0.0)
Requires-Dist: webdriver-manager (>=3.8.3,<4.0.0)
Project-URL: Repository, https://github.com/bennord/cafelogin
